if_else/__init__.py
if_else/mycode.py
if_else/run.py
change_name-0.0.1.dist-info/LICENSE
change_name-0.0.1.dist-info/METADATA
change_name-0.0.1.dist-info/WHEEL
change_name-0.0.1.dist-info/top_level.txt
change_name-0.0.1.dist-info/RECORD
